spark_command_airflow_operator/__init__.py
spark_command_airflow_operator/src/__init__.py
spark_command_airflow_operator/src/dag/__init__.py
spark_command_airflow_operator/src/dag/spark_command_submit_dag.py
spark_command_airflow_operator/src/operator/__init__.py
spark_command_airflow_operator/src/operator/spark_command_submit_operator.py
spark_command_airflow_operator-0.1.3.dist-info/LICENSE.txt
spark_command_airflow_operator-0.1.3.dist-info/METADATA
spark_command_airflow_operator-0.1.3.dist-info/WHEEL
spark_command_airflow_operator-0.1.3.dist-info/RECORD
