Metadata-Version: 2.1
Name: spark-command-airflow-operator
Version: 0.1.3
Summary: 
Author: Sigmar Stefansson
Author-email: sigmarkarl@hotmail.com
Requires-Python: >=3.9,<4.0
Classifier: Programming Language :: Python :: 3
Classifier: Programming Language :: Python :: 3.9
Classifier: Programming Language :: Python :: 3.10
Classifier: Programming Language :: Python :: 3.11
Requires-Dist: apache-airflow (>=2.5.3,<3.0.0)
